pyborg/__init__.py
pyborg/__main__.py
pyborg/cli.py
pyborg/pyborg.py
pyborg_wrapper-0.1.0.dist-info/licenses/LICENSE
pyborg_wrapper-0.1.0.dist-info/METADATA
pyborg_wrapper-0.1.0.dist-info/WHEEL
pyborg_wrapper-0.1.0.dist-info/entry_points.txt
pyborg_wrapper-0.1.0.dist-info/top_level.txt
pyborg_wrapper-0.1.0.dist-info/RECORD
