Metadata-Version: 2.4
Name: pyborg-wrapper
Version: 0.1.0
Summary: A wrapper for borgbackup scripts
Author-email: Alexandre Dareau <alexandre.dareau@protonmail.com>
Maintainer-email: Alexandre Dareau <alexandre.dareau@protonmail.com>
License: GPL-3.0-or-later
Project-URL: Homepage, https://github.com/adareau/pyborg
Project-URL: Repository, https://github.com/adareau/pyborg.git
Project-URL: Issues, https://github.com/adareau/pyborg/issues
Keywords: borgbackup,backups
Classifier: Development Status :: 3 - Alpha
Classifier: Intended Audience :: End Users/Desktop
Classifier: Topic :: System :: Archiving :: Backup
Classifier: Programming Language :: Python :: 3
Classifier: Programming Language :: Python :: 3.10
Requires-Python: >=3.12
License-File: LICENSE
Requires-Dist: typer==0.15.1
Dynamic: license-file
